pyobigram/client.py
pyobigram/inline.py
pyobigram/paralleltransfer.py
pyobigram/readers.py
pyobigram/threads.py
pyobigram/ttui.py
pyobigram/utils.py
pyobigram/version.py
pyobigram-2.1.1.dist-info/LICENSE
pyobigram-2.1.1.dist-info/METADATA
pyobigram-2.1.1.dist-info/WHEEL
pyobigram-2.1.1.dist-info/top_level.txt
pyobigram-2.1.1.dist-info/zip-safe
pyobigram-2.1.1.dist-info/RECORD
