Metadata-Version: 2.1
Name: pyobigram
Version: 2.1.1
Summary: Python 3 library for telegram bots
Home-page: https://github.com/ObisoftDev/pyobigram
Author: ObisoftDev
Author-email: obysoftt@gmail.com
License: The Unlicense (Unlicense)
Keywords: telegram,download,stream,bots
Classifier: Development Status :: 5 - Production/Stable
Classifier: Environment :: Console
Classifier: Intended Audience :: Developers
Classifier: License :: OSI Approved :: The Unlicense (Unlicense)
Classifier: Natural Language :: English
Classifier: Operating System :: OS Independent
Classifier: Programming Language :: Python :: 3.6
Classifier: Programming Language :: Python :: 3.7
Classifier: Programming Language :: Python :: 3.8
Classifier: Programming Language :: Python :: 3.9
Classifier: Programming Language :: Python
Classifier: Topic :: Internet
Classifier: Topic :: Software Development :: Libraries :: Python Modules
Classifier: Topic :: Utilities
Requires-Python: >=3.6
License-File: LICENSE
Requires-Dist: bs4
Requires-Dist: requests
Requires-Dist: requests[socks]
Requires-Dist: user-agent
Requires-Dist: telethon
Requires-Dist: cryptg
